dispatchly/__init__.py
dispatchly/core/__init__.py
dispatchly/tests/__init__.py
dispatchly/tests/test_1.py
dispatchly/tests/test_1984.py
dispatchly/tests/test_2.py
dispatchly-0.0.6.dev0.dist-info/LICENSE.txt
dispatchly-0.0.6.dev0.dist-info/METADATA
dispatchly-0.0.6.dev0.dist-info/WHEEL
dispatchly-0.0.6.dev0.dist-info/top_level.txt
dispatchly-0.0.6.dev0.dist-info/RECORD
