Metadata-Version: 2.1
Name: dispatchly
Version: 0.0.6.dev0
Summary: dispatchly
Author-email: Johannes <johannes-programming@mailfence.com>
License: The MIT License (MIT)
Project-URL: Documentation, https://dispatchly.johannes-programming.online/
Project-URL: Download, https://pypi.org/project/dispatchly/#files
Project-URL: Index, https://pypi.org/project/dispatchly
Project-URL: Source, https://github.com/johannes-programming/dispatchly
Classifier: Development Status :: 2 - Pre-Alpha
Classifier: License :: OSI Approved :: MIT License
Classifier: Programming Language :: Python
Classifier: Programming Language :: Python :: 3
Classifier: Programming Language :: Python :: 3 :: Only
Requires-Python: >=3.8
License-File: LICENSE.txt
Requires-Dist: tofunc>=1.0.0
